LICENSE
MANIFEST.in
setup.cfg
setup.py
versioneer.py
engarde/__init__.py
engarde/_version.py
engarde/checks.py
engarde/decorators.py
engarde/generic.py
topper_123_engarde.egg-info/PKG-INFO
topper_123_engarde.egg-info/SOURCES.txt
topper_123_engarde.egg-info/dependency_links.txt
topper_123_engarde.egg-info/requires.txt
topper_123_engarde.egg-info/top_level.txt