Metadata-Version: 1.1
Name: topper-123-engarde
Version: 0.3.4
Summary: A python package for defensive data analysis.
Home-page: https://github.com/topper-123/engarde
Author: Topper-123 (Originally Tom Augsburger)
Author-email: terji78@gmail.com
License: MIT
Keywords: data analysis
Platform: UNKNOWN
Classifier: Development Status :: 3 - Alpha
Classifier: Intended Audience :: Developers
Classifier: License :: OSI Approved :: MIT License
Classifier: Programming Language :: Python :: 2
Classifier: Programming Language :: Python :: 2.7
Classifier: Programming Language :: Python :: 3
Classifier: Programming Language :: Python :: 3.4
